{
  "id": "session_20251222_018",
  "type": "script_generation",
  "created_at": "2025-12-22T21:23:06.386584",
  "updated_at": "2025-12-22T21:23:06.403236",
  "profile": "ai.for.mortals",
  "history": [],
  "constraints_used": [],
  "feedback": null,
  "metadata": {
    "topic": "Unlock FREE, Pro-Level Video Editing with Cursor 2025 & Runway Gen-4: A 60-Second Workflow  Boost 🚀",
    "hook_text": "Level up your video editing without breaking the bank! Today, we're mastering pro-level results using free tools.",
    "hook_type": "statement",
    "segment_count": 8,
    "word_count": 204,
    "estimated_duration": 81.60000000000001,
    "target_duration": 60.0
  }
}